seokar/__init__.py
seokar/seokar.py
seokar-1.0.0.dist-info/licenses/LICENSE
seokar-1.0.0.dist-info/METADATA
seokar-1.0.0.dist-info/WHEEL
seokar-1.0.0.dist-info/top_level.txt
seokar-1.0.0.dist-info/RECORD
