Metadata-Version: 2.4
Name: seokar
Version: 1.0.0
Summary: A Python library for comprehensive on-page SEO analysis of HTML content.
Author-email: Sajjad Akbari <sajjadakbari.ir@email.com>
License-Expression: MIT
Project-URL: Homepage, https://github.com/sajjadeakbari/seokar
Project-URL: Bug Tracker, https://github.com/sajjadeakbari/seokar/issues
Project-URL: Documentation, https://github.com/sajjadeakbari/seokar#readme
Keywords: seo,seo analysis,html parser,meta tags,opengraph,twitter card,on-page seo,website analysis
Classifier: Development Status :: 3 - Alpha
Classifier: Intended Audience :: Developers
Classifier: Intended Audience :: Information Technology
Classifier: Topic :: Software Development :: Libraries :: Python Modules
Classifier: Topic :: Internet :: WWW/HTTP :: Indexing/Search
Classifier: Topic :: Text Processing :: Markup :: HTML
Classifier: Programming Language :: Python :: 3
Classifier: Programming Language :: Python :: 3.8
Classifier: Programming Language :: Python :: 3.9
Classifier: Programming Language :: Python :: 3.10
Classifier: Programming Language :: Python :: 3.11
Classifier: Programming Language :: Python :: 3.12
Classifier: Operating System :: OS Independent
Classifier: Typing :: Typed
Requires-Python: >=3.8
License-File: LICENSE
Requires-Dist: beautifulsoup4>=4.9.3
Provides-Extra: test
Requires-Dist: pytest>=7.0; extra == "test"
Dynamic: license-file
